[
    {
        "type": "金融",
        "top": [
            {
                "name": "支付宝钱包",
                "icon": "ff1647549ff003044b10febf21081638_256_256.png",
                "install_num":92163148
            },
            {
                "name": "小米金融",
                "icon": "3056078b5665b46ca8fa192b293cf990_256_256.png",
                "install_num":13491261
            },
            {
                "name": "中国建设银行",
                "icon": "7cbc753b056fb7ad3cfe34dcda70b390_256_256.png",
                "install_num":12659716
            },
            {
                "name": "工行手机银行",
                "icon": "62e20fbf499e798e0373165fccf706b3_256_256.png",
                "install_num":8887919
            },
            {
                "name": "农行掌上银行",
                "icon": "ab1a6919c168ca5793bad5966da96ad6_256_256.png",
                "install_num":6472767
            },
            {
                "name": "同花顺",
                "icon": "6b4d02ddb438f831fd4d4648fb042d5c_256_256.png",
                "install_num":6097914
            }
        ]
    },
    {
        "type": "母婴",
        "top": [
            {
                "name": "宝宝树孕育",
                "icon": "86cf9adb62b12dc61d25b070ae5e7547_256_256.png",
                "install_num":7495112
            },
            {
                "name": "贝贝特卖",
                "icon": "t0115d3093eab09e0bd.png",
                "install_num":3328437
            },
            {
                "name": "美柚孕期",
                "icon": "f2da9ab9ff872576d774f85de64a7d3a_256_256.png",
                "install_num":1429891
            },
            {
                "name": "妈妈帮",
                "icon": "8c62df406549c51ffc5e386f832e98de_256_256.png",
                "install_num":922971
            },
            {
                "name": "蜜芽宝贝",
                "icon": "9e7e56a1d3651b6bf777c2c1d4ce3727_256_256.png",
                "install_num":830202
            },
            {
                "name": "宝宝树时光",
                "icon": "0a1fcc65743dd9decc611748f8a85124_256_256.png",
                "install_num":786837
            }
        ]
    },
    {
        "type": "旅行",
        "top": [
            {
                "name": "去哪儿旅行",
                "icon": "96.png",
                "install_num":17149209
            },
            {
                "name": "铁路12306",
                "icon": "33b64c4e680d0d6721a8366ba79641b0_256_256.png",
                "install_num":16972948
            },
            {
                "name": "携程旅行",
                "icon": "t013ad35e45eea956c3.png",
                "install_num":12439567
            },
            {
                "name": "途牛旅游",
                "icon": "t01f9a27f521e04a283.png",
                "install_num":5060344
            },
            {
                "name": "同程旅游",
                "icon": "t011ff2884c2c9d7754.png",
                "install_num":4349740
            },
            {
                "name": "阿里旅行",
                "icon": "t0162cb8876fee4560a.png",
                "install_num":4243137
            }
        ]
    },
    {
        "type": "社交",
        "top": [
            {
                "name": "微信",
                "icon": "15891412e00a12fdec0bbe290b42ced7_256_256.png",
                "install_num":201054838
            },
            {
                "name": "QQ",
                "icon": "4764bbc6717fe399db4eb2e5e41342a6_256_256.png",
                "install_num":177426524
            },
            {
                "name": "微博",
                "icon": "dedacdf1884dafceff65a20dea89a39e_256_256.png",
                "install_num":56135224
            },
            {
                "name": "QQ空间",
                "icon": "9b5b12f437d30cdf8361827f642e3f3d_256_256.png",
                "install_num":26775837
            },
            {
                "name": "全民K歌",
                "icon": "c42926430211aad8f8119e7a384ba03e_256_256.png",
                "install_num":24017745
            },
            {
                "name": "陌陌",
                "icon": "5e7c57624abf5df52300f47b79f3fc39_256_256.png",
                "install_num":14506595
            }
        ]
    }
]