[{"city":"天津市", "ratio":2770},
  {"city":"香港特别行政区", "ratio":2569},
  {"city":"沈阳市", "ratio":794},
  {"city":"石家庄市", "ratio":703},
  {"city":"西安市", "ratio":560},
  {"city":"上海市", "ratio":442},
  {"city":"温州市", "ratio":422},
  {"city":"济宁市", "ratio":409},
  {"city":"常州市", "ratio":399},
  {"city":"广州市", "ratio":325},
  {"city":"保定市", "ratio":265},
  {"city":"廊坊市", "ratio":261},
  {"city":"太原市", "ratio":241},
  {"city":"郑州市", "ratio":230},
  {"city":"福州市", "ratio":222},
  {"city":"青岛市", "ratio":190},
  {"city":"济南市", "ratio":177},
  {"city":"null", "ratio":172},
  {"city":"深圳市", "ratio":171},
  {"city":"乌鲁木齐市", "ratio":165},
  {"city":"杭州市", "ratio":159},
  {"city":"呼和浩特市", "ratio":147},
  {"city":"武汉市", "ratio":145},
  {"city":"昆明市", "ratio":142},
  {"city":"成都市", "ratio":140},
  {"city":"通辽市", "ratio":125},
  {"city":"秦皇岛市", "ratio":119},
  {"city":"湖州市", "ratio":115},
  {"city":"长治市", "ratio":114},
  {"city":"滨州市", "ratio":111},
  {"city":"张家口市", "ratio":100},
  {"city":"南京市", "ratio":98},
  {"city":"哈尔滨市", "ratio":98},
  {"city":"唐山市", "ratio":95},
  {"city":"承德市", "ratio":93},
  {"city":"重庆市", "ratio":89},
  {"city":"泉州市", "ratio":85},
  {"city":"海口市", "ratio":80},
  {"city":"长春市", "ratio":78},
  {"city":"邯郸市", "ratio":76},
  {"city":"烟台市", "ratio":75},
  {"city":"南昌市", "ratio":74},
  {"city":"辽阳市", "ratio":69},
  {"city":"沧州市", "ratio":64},
  {"city":"舟山市", "ratio":64},
  {"city":"邢台市", "ratio":63},
  {"city":"忻州市", "ratio":63},
  {"city":"大连市", "ratio":62},
  {"city":"合肥市", "ratio":61},
  {"city":"龙岩市", "ratio":60},
  {"city":"吉林市", "ratio":58},
  {"city":"潍坊市", "ratio":58},
  {"city":"长沙市", "ratio":50},
  {"city":"南宁市", "ratio":50},
  {"city":"临沂市", "ratio":50},
  {"city":"晋中市", "ratio":48},
  {"city":"阳泉市", "ratio":47},
  {"city":"泰安市", "ratio":47},
  {"city":"宁波市", "ratio":45},
  {"city":"岳阳市", "ratio":45},
  {"city":"厦门市", "ratio":44},
  {"city":"威海市", "ratio":42},
  {"city":"菏泽市", "ratio":41},
  {"city":"娄底市", "ratio":41},
  {"city":"淄博市", "ratio":40},
  {"city":"渭南市", "ratio":38},
  {"city":"宝鸡市", "ratio":37},
  {"city":"晋城市", "ratio":36},
  {"city":"台州市", "ratio":36},
  {"city":"汉中市", "ratio":34},
  {"city":"阜新市", "ratio":34},
  {"city":"聊城市", "ratio":34},
  {"city":"洛阳市", "ratio":31},
  {"city":"德州市", "ratio":31},
  {"city":"衡水市", "ratio":31},
  {"city":"苏州市", "ratio":30},
  {"city":"赣州市", "ratio":30},
  {"city":"兰州市", "ratio":29},
  {"city":"佛山市", "ratio":29},
  {"city":"运城市", "ratio":28},
  {"city":"赤峰市", "ratio":27},
  {"city":"葫芦岛市", "ratio":27},
  {"city":"宜昌市", "ratio":26},
  {"city":"嘉兴市", "ratio":26},
  {"city":"台湾省", "ratio":25},
  {"city":"遵义市", "ratio":25},
  {"city":"大同市", "ratio":24},
  {"city":"鞍山市", "ratio":24},
  {"city":"抚顺市", "ratio":24},
  {"city":"包头市", "ratio":21},
  {"city":"焦作市", "ratio":20},
  {"city":"安阳市", "ratio":20},
  {"city":"南平市", "ratio":19},
  {"city":"滁州市", "ratio":19},
  {"city":"无锡市", "ratio":19},
  {"city":"三亚市", "ratio":19},
  {"city":"锦州市", "ratio":18},
  {"city":"营口市", "ratio":18},
  {"city":"宁德市", "ratio":18},
  {"city":"荆州市", "ratio":17}]